telebotify/__init__.py
telebotify/bot_base.py
telebotify/models/__init__.py
telebotify/models/body.py
telebotify/models/chat.py
telebotify/models/jsonable.py
telebotify/models/message.py
telebotify/models/update.py
telebotify/models/user.py
telebotify/resources/__init__.py
telebotify/resources/i18n/es.json
telebotify/services/__init__.py
telebotify/services/http_client.py
telebotify/utils/__init__.py
telebotify/utils/file_utils.py
telebotify/utils/model_mapper.py
tests/__init__.py
tests/test.py
telebotify-0.1.12.dist-info/METADATA
telebotify-0.1.12.dist-info/WHEEL
telebotify-0.1.12.dist-info/top_level.txt
telebotify-0.1.12.dist-info/RECORD
