Metadata-Version: 2.1
Name: telebotify
Version: 0.1.12
Summary: A Python library for developing Telegram bots
Home-page: UNKNOWN
Author: Alejandro de Felipe
License: MIT
Platform: UNKNOWN
